[
  {
    "Driver": "ALB",
    "Stint": 1.0,
    "Compound": "MEDIUM",
    "start_lap": 1,
    "end_lap": 13,
    "lap_count": 13,
    "tyre_life_at_end": 12
  },
  {
    "Driver": "ALB",
    "Stint": 2.0,
    "Compound": "MEDIUM",
    "start_lap": 14,
    "end_lap": 15,
    "lap_count": 2,
    "tyre_life_at_end": 1
  },
  {
    "Driver": "ALO",
    "Stint": 1.0,
    "Compound": "MEDIUM",
    "start_lap": 1,
    "end_lap": 33,
    "lap_count": 33,
    "tyre_life_at_end": 33
  },
  {
    "Driver": "ALO",
    "Stint": 2.0,
    "Compound": "HARD",
    "start_lap": 34,
    "end_lap": 69,
    "lap_count": 36,
    "tyre_life_at_end": 36
  },
  {
    "Driver": "ANT",
    "Stint": 1.0,
    "Compound": "MEDIUM",
    "start_lap": 1,
    "end_lap": 1,
    "lap_count": 1,
    "tyre_life_at_end": 0
  },
  {
    "Driver": "BEA",
    "Stint": 1.0,
    "Compound": "SOFT",
    "start_lap": 1,
    "end_lap": 11,
    "lap_count": 11,
    "tyre_life_at_end": 10
  },
  {
    "Driver": "BEA",
    "Stint": 2.0,
    "Compound": "HARD",
    "start_lap": 12,
    "end_lap": 39,
    "lap_count": 28,
    "tyre_life_at_end": 27
  },
  {
    "Driver": "BEA",
    "Stint": 3.0,
    "Compound": "MEDIUM",
    "start_lap": 40,
    "end_lap": 69,
    "lap_count": 30,
    "tyre_life_at_end": 29
  },
  {
    "Driver": "BOR",
    "Stint": 1.0,
    "Compound": "MEDIUM",
    "start_lap": 1,
    "end_lap": 21,
    "lap_count": 21,
    "tyre_life_at_end": 20
  },
  {
    "Driver": "BOR",
    "Stint": 2.0,
    "Compound": "MEDIUM",
    "start_lap": 22,
    "end_lap": 49,
    "lap_count": 28,
    "tyre_life_at_end": 27
  },
  {
    "Driver": "BOR",
    "Stint": 3.0,
    "Compound": "HARD",
    "start_lap": 50,
    "end_lap": 69,
    "lap_count": 20,
    "tyre_life_at_end": 19
  },
  {
    "Driver": "COL",
    "Stint": 1.0,
    "Compound": "SOFT",
    "start_lap": 1,
    "end_lap": 13,
    "lap_count": 13,
    "tyre_life_at_end": 12
  },
  {
    "Driver": "COL",
    "Stint": 2.0,
    "Compound": "MEDIUM",
    "start_lap": 14,
    "end_lap": 39,
    "lap_count": 26,
    "tyre_life_at_end": 25
  },
  {
    "Driver": "COL",
    "Stint": 3.0,
    "Compound": "HARD",
    "start_lap": 40,
    "end_lap": 69,
    "lap_count": 30,
    "tyre_life_at_end": 29
  },
  {
    "Driver": "GAS",
    "Stint": 1.0,
    "Compound": "SOFT",
    "start_lap": 1,
    "end_lap": 12,
    "lap_count": 12,
    "tyre_life_at_end": 14
  },
  {
    "Driver": "GAS",
    "Stint": 2.0,
    "Compound": "HARD",
    "start_lap": 13,
    "end_lap": 38,
    "lap_count": 26,
    "tyre_life_at_end": 25
  },
  {
    "Driver": "GAS",
    "Stint": 3.0,
    "Compound": "MEDIUM",
    "start_lap": 39,
    "end_lap": 69,
    "lap_count": 31,
    "tyre_life_at_end": 30
  },
  {
    "Driver": "HAD",
    "Stint": 1.0,
    "Compound": "SOFT",
    "start_lap": 1,
    "end_lap": 2,
    "lap_count": 2,
    "tyre_life_at_end": 1
  },
  {
    "Driver": "HAD",
    "Stint": 2.0,
    "Compound": "MEDIUM",
    "start_lap": 3,
    "end_lap": 28,
    "lap_count": 26,
    "tyre_life_at_end": 25
  },
  {
    "Driver": "HAD",
    "Stint": 3.0,
    "Compound": "HARD",
    "start_lap": 29,
    "end_lap": 69,
    "lap_count": 41,
    "tyre_life_at_end": 40
  },
  {
    "Driver": "HAM",
    "Stint": 1.0,
    "Compound": "MEDIUM",
    "start_lap": 1,
    "end_lap": 26,
    "lap_count": 26,
    "tyre_life_at_end": 25
  },
  {
    "Driver": "HAM",
    "Stint": 2.0,
    "Compound": "HARD",
    "start_lap": 27,
    "end_lap": 50,
    "lap_count": 24,
    "tyre_life_at_end": 23
  },
  {
    "Driver": "HAM",
    "Stint": 3.0,
    "Compound": "MEDIUM",
    "start_lap": 51,
    "end_lap": 70,
    "lap_count": 20,
    "tyre_life_at_end": 19
  },
  {
    "Driver": "HUL",
    "Stint": 1.0,
    "Compound": "SOFT",
    "start_lap": 1,
    "end_lap": 12,
    "lap_count": 12,
    "tyre_life_at_end": 11
  },
  {
    "Driver": "HUL",
    "Stint": 2.0,
    "Compound": "MEDIUM",
    "start_lap": 13,
    "end_lap": 42,
    "lap_count": 30,
    "tyre_life_at_end": 29
  },
  {
    "Driver": "HUL",
    "Stint": 3.0,
    "Compound": "MEDIUM",
    "start_lap": 43,
    "end_lap": 69,
    "lap_count": 27,
    "tyre_life_at_end": 26
  },
  {
    "Driver": "LAW",
    "Stint": 1.0,
    "Compound": "MEDIUM",
    "start_lap": 1,
    "end_lap": 32,
    "lap_count": 32,
    "tyre_life_at_end": 31
  },
  {
    "Driver": "LAW",
    "Stint": 2.0,
    "Compound": "HARD",
    "start_lap": 33,
    "end_lap": 70,
    "lap_count": 38,
    "tyre_life_at_end": 37
  },
  {
    "Driver": "LEC",
    "Stint": 1.0,
    "Compound": "MEDIUM",
    "start_lap": 1,
    "end_lap": 25,
    "lap_count": 25,
    "tyre_life_at_end": 24
  },
  {
    "Driver": "LEC",
    "Stint": 2.0,
    "Compound": "HARD",
    "start_lap": 26,
    "end_lap": 49,
    "lap_count": 24,
    "tyre_life_at_end": 23
  },
  {
    "Driver": "LEC",
    "Stint": 3.0,
    "Compound": "MEDIUM",
    "start_lap": 50,
    "end_lap": 70,
    "lap_count": 21,
    "tyre_life_at_end": 20
  },
  {
    "Driver": "NOR",
    "Stint": 1.0,
    "Compound": "MEDIUM",
    "start_lap": 1,
    "end_lap": 20,
    "lap_count": 20,
    "tyre_life_at_end": 19
  },
  {
    "Driver": "NOR",
    "Stint": 2.0,
    "Compound": "HARD",
    "start_lap": 21,
    "end_lap": 52,
    "lap_count": 32,
    "tyre_life_at_end": 31
  },
  {
    "Driver": "NOR",
    "Stint": 3.0,
    "Compound": "MEDIUM",
    "start_lap": 53,
    "end_lap": 70,
    "lap_count": 18,
    "tyre_life_at_end": 17
  },
  {
    "Driver": "OCO",
    "Stint": 1.0,
    "Compound": "MEDIUM",
    "start_lap": 1,
    "end_lap": 19,
    "lap_count": 19,
    "tyre_life_at_end": 18
  },
  {
    "Driver": "OCO",
    "Stint": 2.0,
    "Compound": "HARD",
    "start_lap": 20,
    "end_lap": 50,
    "lap_count": 31,
    "tyre_life_at_end": 30
  },
  {
    "Driver": "OCO",
    "Stint": 3.0,
    "Compound": "HARD",
    "start_lap": 51,
    "end_lap": 69,
    "lap_count": 19,
    "tyre_life_at_end": 18
  },
  {
    "Driver": "PIA",
    "Stint": 1.0,
    "Compound": "MEDIUM",
    "start_lap": 1,
    "end_lap": 24,
    "lap_count": 24,
    "tyre_life_at_end": 23
  },
  {
    "Driver": "PIA",
    "Stint": 2.0,
    "Compound": "HARD",
    "start_lap": 25,
    "end_lap": 53,
    "lap_count": 29,
    "tyre_life_at_end": 28
  },
  {
    "Driver": "PIA",
    "Stint": 3.0,
    "Compound": "MEDIUM",
    "start_lap": 54,
    "end_lap": 70,
    "lap_count": 17,
    "tyre_life_at_end": 16
  },
  {
    "Driver": "RUS",
    "Stint": 1.0,
    "Compound": "MEDIUM",
    "start_lap": 1,
    "end_lap": 18,
    "lap_count": 18,
    "tyre_life_at_end": 17
  },
  {
    "Driver": "RUS",
    "Stint": 2.0,
    "Compound": "MEDIUM",
    "start_lap": 19,
    "end_lap": 45,
    "lap_count": 27,
    "tyre_life_at_end": 26
  },
  {
    "Driver": "RUS",
    "Stint": 3.0,
    "Compound": "HARD",
    "start_lap": 46,
    "end_lap": 70,
    "lap_count": 25,
    "tyre_life_at_end": 24
  },
  {
    "Driver": "SAI",
    "Stint": 1.0,
    "Compound": "MEDIUM",
    "start_lap": 1,
    "end_lap": 1,
    "lap_count": 1,
    "tyre_life_at_end": 0
  },
  {
    "Driver": "STR",
    "Stint": 1.0,
    "Compound": "MEDIUM",
    "start_lap": 1,
    "end_lap": 26,
    "lap_count": 26,
    "tyre_life_at_end": 26
  },
  {
    "Driver": "STR",
    "Stint": 2.0,
    "Compound": "HARD",
    "start_lap": 27,
    "end_lap": 53,
    "lap_count": 27,
    "tyre_life_at_end": 27
  },
  {
    "Driver": "STR",
    "Stint": 3.0,
    "Compound": "SOFT",
    "start_lap": 54,
    "end_lap": 69,
    "lap_count": 16,
    "tyre_life_at_end": 15
  },
  {
    "Driver": "TSU",
    "Stint": 1.0,
    "Compound": "MEDIUM",
    "start_lap": 1,
    "end_lap": 18,
    "lap_count": 18,
    "tyre_life_at_end": 17
  },
  {
    "Driver": "TSU",
    "Stint": 2.0,
    "Compound": "HARD",
    "start_lap": 19,
    "end_lap": 30,
    "lap_count": 12,
    "tyre_life_at_end": 11
  },
  {
    "Driver": "TSU",
    "Stint": 3.0,
    "Compound": "MEDIUM",
    "start_lap": 31,
    "end_lap": 60,
    "lap_count": 30,
    "tyre_life_at_end": 29
  },
  {
    "Driver": "TSU",
    "Stint": 4.0,
    "Compound": "SOFT",
    "start_lap": 61,
    "end_lap": 68,
    "lap_count": 8,
    "tyre_life_at_end": 7
  },
  {
    "Driver": "VER",
    "Stint": 1.0,
    "Compound": "MEDIUM",
    "start_lap": 1,
    "end_lap": 1,
    "lap_count": 1,
    "tyre_life_at_end": 0
  }
]