{
  "scraped_at": "2026-07-09T09:38:28.772377+00:00",
  "ratings": {
    "Spain": 2226,
    "Argentina": 2287,
    "France": 2298,
    "England": 2054,
    "Brazil": 2063,
    "Portugal": 1956,
    "Colombia": 2076,
    "Netherlands": 2057,
    "Ecuador": 1853,
    "Germany": 1862,
    "Norway": 2005,
    "Croatia": 1928,
    "Turkey": 1722,
    "Japan": 1937,
    "Belgium": 1827,
    "Uruguay": 1707,
    "Switzerland": 1829,
    "Mexico": 2069,
    "Senegal": 1724,
    "Paraguay": 1809,
    "Austria": 1851,
    "Morocco": 2070,
    "Canada": 1707,
    "Scotland": 1677,
    "Australia": 1815,
    "Algeria": 1837,
    "Iran": 1740,
    "South Korea": 1414,
    "Czech Republic": 1740,
    "Panama": 1391,
    "USA": 1902,
    "Uzbekistan": 1469,
    "Sweden": 1818,
    "Egypt": 1830,
    "Ivory Coast": 1850,
    "Jordan": 1422,
    "Congo DR": 1836,
    "Tunisia": 1382,
    "Iraq": 1417,
    "Bosnia and Herzegovina": 1595,
    "Cabo Verde": 1578,
    "Saudi Arabia": 1692,
    "New Zealand": 1527,
    "Haiti": 1338,
    "South Africa": 1667,
    "Ghana": 1803,
    "Curacao": 1434,
    "Qatar": 1564,
    "Kenya": 1356
  }
}